tests/app/__init__.py
tests/app/urls.py
wapps/__init__.py
wapps/admin.py
wapps/api.py
wapps/apps.py
wapps/babel.cfg
wapps/context_processors.py
wapps/debug_toolbar.py
wapps/errors.py
wapps/feed.py
wapps/image_formats.py
wapps/json.py
wapps/jsonld.py
wapps/metadata.py
wapps/middleware.py
wapps/mixins.py
wapps/pytest.py
wapps/social.py
wapps/tests.py
wapps/urls.py
wapps/utils.py
wapps/views.py
wapps/wagtail_hooks.py
wapps/blog/__init__.py
wapps/blog/apps.py
wapps/blog/babel.cfg
wapps/blog/factories.py
wapps/blog/feeds.py
wapps/blog/models.py
wapps/blog/utils.py
wapps/blog/wagtail_hooks.py
wapps/blog/jinja2/blog/blog.html
wapps/blog/jinja2/blog/blog_post.html
wapps/blog/jinja2/blog/metadata.html
wapps/blog/locale/es/LC_MESSAGES/django.mo
wapps/blog/locale/es/LC_MESSAGES/django.po
wapps/blog/locale/fr/LC_MESSAGES/django.mo
wapps/blog/locale/fr/LC_MESSAGES/django.po
wapps/blog/migrations/0001_initial.py
wapps/blog/migrations/0002_excerpt_as_text.py
wapps/blog/migrations/0003_blog_image.py
wapps/blog/migrations/__init__.py
wapps/blog/templatetags/__init__.py
wapps/blog/templatetags/blog.py
wapps/comments/__init__.py
wapps/comments/apps.py
wapps/comments/babel.cfg
wapps/comments/feeds.py
wapps/comments/models.py
wapps/comments/utils.py
wapps/comments/wagtail_hooks.py
wapps/comments/jinja2/blog/blog.html
wapps/comments/jinja2/blog/blog_post.html
wapps/comments/jinja2/blog/metadata.html
wapps/comments/templatetags/__init__.py
wapps/comments/templatetags/comments.py
wapps/factories/__init__.py
wapps/factories/category.py
wapps/factories/django-logo-negative.svg
wapps/factories/django-logo-positive.svg
wapps/factories/identity.py
wapps/factories/image.py
wapps/factories/pages.py
wapps/factories/request.py
wapps/factories/site.py
wapps/factories/tag.py
wapps/factories/user.py
wapps/factories/wagtail.svg
wapps/forms/__init__.py
wapps/forms/apps.py
wapps/forms/babel.cfg
wapps/forms/blocks.py
wapps-0.1.2.dev0.dist-info/DESCRIPTION.rst
wapps-0.1.2.dev0.dist-info/METADATA
wapps-0.1.2.dev0.dist-info/RECORD
wapps-0.1.2.dev0.dist-info/WHEEL
wapps-0.1.2.dev0.dist-info/entry_points.txt
wapps-0.1.2.dev0.dist-info/metadata.json
wapps-0.1.2.dev0.dist-info/top_level.txt
